MANIFEST.in
README.md
setup.py
awsscheduler/__init__.py
awsscheduler/scheduler.py
uniplaces_aws_scheduler.egg-info/PKG-INFO
uniplaces_aws_scheduler.egg-info/SOURCES.txt
uniplaces_aws_scheduler.egg-info/dependency_links.txt
uniplaces_aws_scheduler.egg-info/entry_points.txt
uniplaces_aws_scheduler.egg-info/not-zip-safe
uniplaces_aws_scheduler.egg-info/requires.txt
uniplaces_aws_scheduler.egg-info/top_level.txt