Metadata-Version: 1.0
Name: uniplaces-aws-scheduler
Version: 1.2.1
Summary: A scheduling script for aws ec2 instances
Home-page: https://github.com/uniplaces/uniplaces-aws-scheduler
Author: mlimaloureiro
Author-email: miguel.loureiro@uniplaces.com
License: MIT
Platform: UNKNOWN
